{"fname":"lang.java.lib","stub":true,"vault":{"fsPath":".","selfContained":true,"name":"cs"},"schemaStub":false,"type":"note","updated":1727379882090,"created":1727379882090,"id":"2iaiw6abjhpczxzzr1tsqep","desc":"","links":[],"anchors":{},"children":["l6kravc26pl7ixjyg5o3nlk","dkdtvct3q6f8lggmoqrqf43","ejs8lnn6txy9zzk51cot50f","q1epee590dzpf5zvcwfd82c","2yvl1jdxsuy6584xzcm4759","vqbisdumti23oeq2xk6oml5","pj5i0tpvpdd5yl27453jvx8","g0uqfqlelznnd4zyjzk9qb3"],"parent":"mrk0ypui29nso2bc2r99pok","data":{},"title":"Lib","schema":{"schemaId":"lib","moduleId":"lang"}}
