{"id":"2yvl1jdxsuy6584xzcm4759","title":"Multithreading","desc":"","updated":1727375344580,"created":1727373800483,"custom":{},"fname":"lang.java.lib.multithreading","type":"note","vault":{"fsPath":".","selfContained":true,"name":"cs"},"contentHash":"6216db4f8df5e4cbb90ff878c48aa8bc","links":[{"type":"wiki","from":{"fname":"lang.java.lib.multithreading","id":"2yvl1jdxsuy6584xzcm4759","vaultName":"cs"},"value":"lang.java.lib.multithreading.thread","position":{"start":{"line":6,"column":11,"offset":45},"end":{"line":6,"column":50,"offset":84},"indent":[]},"xvault":false,"sameFile":false,"to":{"fname":"lang.java.lib.multithreading.thread"}},{"type":"wiki","from":{"fname":"lang.java.lib.multithreading","id":"2yvl1jdxsuy6584xzcm4759","vaultName":"cs"},"value":"lang.java.lib.multithreading.runnable","position":{"start":{"line":7,"column":14,"offset":104},"end":{"line":7,"column":55,"offset":145},"indent":[]},"xvault":false,"sameFile":false,"to":{"fname":"lang.java.lib.multithreading.runnable"}},{"type":"wiki","from":{"fname":"lang.java.lib.multithreading","id":"2yvl1jdxsuy6584xzcm4759","vaultName":"cs"},"value":"lang.java.lib.multithreading.executor service","position":{"start":{"line":29,"column":7,"offset":753},"end":{"line":29,"column":56,"offset":802},"indent":[]},"xvault":false,"sameFile":false,"to":{"fname":"lang.java.lib.multithreading.executor service"}},{"from":{"fname":"lang.java.concurrency.multithreading","id":"jik03wh5g5jxxfz2aklbmub","vaultName":"cs"},"type":"backlink","position":{"start":{"line":2,"column":24,"offset":24},"end":{"line":2,"column":56,"offset":56},"indent":[]},"value":"lang.java.lib.multithreading"}],"anchors":{"creating-a-thread":{"type":"header","text":"Creating a thread","value":"creating-a-thread","line":8,"column":0,"depth":3},"executing-threads":{"type":"header","text":"Executing Threads","value":"executing-threads","line":17,"column":0,"depth":3}},"children":["9tn4qoat4ksb1kha3p77zhe","hp20nwapkvz478u3jq2ok1a","mg03s0pff7h5ot8rl438gdr"],"parent":"2iaiw6abjhpczxzzr1tsqep","data":{}}
