{"fname":"lang.java","stub":true,"vault":{"fsPath":".","selfContained":true,"name":"cs"},"schemaStub":false,"type":"note","updated":1722604425727,"created":1722604425727,"id":"76yyzmwlbym3ol10oc56kz8","desc":"","links":[],"anchors":{},"children":["qrw97vn9y1kh2vunbuqa2md","0ru6kcz5oabw4407rcnzgva","vtssw70mxi17onoif07cght","gnqzf0k4jeg5f1a0o88l7iw","elkzjykoygfv9srvii8n1yx","p8j0iu011t7kiz32mtlcbpp","ithet47gft6sdz8aver15fe","7can84kl3rwuwg746ec219l","y2oc1fajxue2tmil2ltgewn","dzonsry93evqozegzzaxrh9","p10wtji5tckz6on3smdtsmc","hcaguz132fadfz4drv90oxf","q5n7lyabbn9ot8ikkv7r5oy"],"parent":"s6z8znku5x57uvq3u9q1po8","data":{},"title":"Java","schema":{"schemaId":"lang","moduleId":"lang"}}
