{"id":"9tn4qoat4ksb1kha3p77zhe","title":"ExecutorService","desc":"","updated":1727374020289,"created":1713125223294,"custom":{},"fname":"lang.java.lib.multithreading.executor service","type":"note","vault":{"fsPath":".","selfContained":true,"name":"cs"},"contentHash":"94223ecd998d5dd0e763e82ee7687294","links":[{"from":{"fname":"lang.java.concurrency.multithreading","id":"jik03wh5g5jxxfz2aklbmub","vaultName":"cs"},"type":"backlink","position":{"start":{"line":45,"column":12,"offset":910},"end":{"line":45,"column":61,"offset":959},"indent":[]},"value":"lang.java.lib.multithreading.executor service"},{"from":{"fname":"lang.java.lib.multithreading","id":"2yvl1jdxsuy6584xzcm4759","vaultName":"cs"},"type":"backlink","position":{"start":{"line":29,"column":7,"offset":753},"end":{"line":29,"column":56,"offset":802},"indent":[]},"value":"lang.java.lib.multithreading.executor service"}],"anchors":{"instantiation-using-executors-factory-class":{"type":"header","text":"Instantiation using Executors Factory class","value":"instantiation-using-executors-factory-class","line":12,"column":0,"depth":2},"for-single-thread":{"type":"header","text":"For single thread","value":"for-single-thread","line":16,"column":0,"depth":3},"for-thread-pool":{"type":"header","text":"For thread pool","value":"for-thread-pool","line":22,"column":0,"depth":3},"for-scheduled-thread-pool":{"type":"header","text":"For scheduled thread pool","value":"for-scheduled-thread-pool","line":28,"column":0,"depth":3},"methods":{"type":"header","text":"Methods","value":"methods","line":35,"column":0,"depth":2},"executing-threads":{"type":"header","text":"Executing Threads","value":"executing-threads","line":37,"column":0,"depth":3},"shutting-down":{"type":"header","text":"Shutting down","value":"shutting-down","line":47,"column":0,"depth":3}},"children":[],"parent":"2yvl1jdxsuy6584xzcm4759","data":{}}
