{"id":"c376iyczea2rtetyc1dgolt","title":"String","desc":"","updated":1727121409413,"created":1712856008805,"custom":{},"fname":"lang.java.jre.memory.string","type":"note","vault":{"fsPath":".","selfContained":true,"name":"cs"},"contentHash":"8c23d4d103517e05549966323ce4b453","links":[{"type":"wiki","from":{"fname":"lang.java.jre.memory.string","id":"c376iyczea2rtetyc1dgolt","vaultName":"cs"},"value":"lang.java.jre.jvm","position":{"start":{"line":9,"column":29,"offset":153},"end":{"line":9,"column":50,"offset":174},"indent":[]},"xvault":false,"sameFile":false,"to":{"fname":"lang.java.jre.jvm"}},{"from":{"fname":"lang.java.lib.string","id":"vqbisdumti23oeq2xk6oml5","vaultName":"cs"},"type":"backlink","position":{"start":{"line":9,"column":1,"offset":308},"end":{"line":9,"column":33,"offset":340},"indent":[]},"value":"lang.java.jre.memory.string"}],"anchors":{"string-constant-pool":{"type":"header","text":"String Constant Pool","value":"string-constant-pool","line":8,"column":0,"depth":2},"string-initialization-using-literals":{"type":"header","text":"String Initialization using literals","value":"string-initialization-using-literals","line":13,"column":0,"depth":2},"string-initialization-using-new":{"type":"header","text":"String Initialization using new","value":"string-initialization-using-new","line":20,"column":0,"depth":2}},"children":[],"parent":"k83mi3ehud8dj1dey48p9iv","data":{}}
