{"id":"eah0wrph9gnljaf0xaflov8","title":"Runtime","desc":"","updated":1708456114857,"created":1708456112735,"custom":{},"fname":"execution.lifecycle.runtime","type":"note","vault":{"fsPath":".","selfContained":true,"name":"cs"},"contentHash":"13e62ad5c1577df887d2893ccdb7de81","links":[{"from":{"fname":"execution.lifecycle","id":"fxxtzg00e2flrfoyfedf7a8","vaultName":"cs"},"type":"backlink","position":{"start":{"line":11,"column":3,"offset":173},"end":{"line":11,"column":34,"offset":204},"indent":[]},"value":"execution.lifecycle.runtime"},{"from":{"fname":"tags.instance-of","id":"sa6ohhgmwap5ji3hxq5glls","vaultName":"cs"},"type":"backlink","position":{"start":{"line":3,"column":48,"offset":49},"end":{"line":3,"column":79,"offset":80},"indent":[]},"value":"execution.lifecycle.runtime"},{"from":{"fname":"os.memory.management","id":"x7nmks70ns14mh5k96w9aov","vaultName":"cs"},"type":"backlink","position":{"start":{"line":33,"column":131,"offset":1112},"end":{"line":33,"column":162,"offset":1143},"indent":[]},"value":"execution.lifecycle.runtime"},{"from":{"fname":"dev.memory management.alloc.dynamic","id":"0cueuj9r6x18l6tbrl3k7w5","vaultName":"cs"},"type":"backlink","position":{"start":{"line":2,"column":25,"offset":25},"end":{"line":2,"column":56,"offset":56},"indent":[]},"value":"execution.lifecycle.runtime"}],"anchors":{},"children":[],"parent":"fxxtzg00e2flrfoyfedf7a8","data":{}}
