{"id":"gnqzf0k4jeg5f1a0o88l7iw","title":"Syntax","desc":"Java Syntax","updated":1714721082175,"created":1709449585041,"custom":{},"fname":"lang.java.syntax","type":"note","vault":{"fsPath":".","selfContained":true,"name":"cs"},"contentHash":"04d513072c539fad2ddf6663f4e74a2d","links":[{"type":"wiki","from":{"fname":"lang.java.syntax","id":"gnqzf0k4jeg5f1a0o88l7iw","vaultName":"cs"},"value":"lang.java.paradigms.oo.instantiation.iib","position":{"start":{"line":64,"column":32,"offset":1330},"end":{"line":64,"column":76,"offset":1374},"indent":[]},"xvault":false,"sameFile":false,"to":{"fname":"lang.java.paradigms.oo.instantiation.iib"}},{"type":"wiki","from":{"fname":"lang.java.syntax","id":"gnqzf0k4jeg5f1a0o88l7iw","vaultName":"cs"},"value":"paradigm.oo.components.modifiers.static","position":{"start":{"line":72,"column":33,"offset":1590},"end":{"line":72,"column":76,"offset":1633},"indent":[]},"xvault":false,"sameFile":false,"to":{"fname":"paradigm.oo.components.modifiers.static"}}],"anchors":{"hello-world":{"type":"header","text":"Hello World","value":"hello-world","line":9,"column":0,"depth":2},"rules":{"type":"header","text":"Rules","value":"rules","line":19,"column":0,"depth":2},"naming-conventions":{"type":"header","text":"Naming Conventions","value":"naming-conventions","line":29,"column":0,"depth":2},"comments":{"type":"header","text":"Comments","value":"comments","line":36,"column":0,"depth":2},"variables":{"type":"header","text":"Variables","value":"variables","line":45,"column":0,"depth":2},"declaration":{"type":"header","text":"Declaration","value":"declaration","line":47,"column":0,"depth":3},"initialization":{"type":"header","text":"Initialization","value":"initialization","line":49,"column":0,"depth":3},"both-at-once":{"type":"header","text":"Both at once","value":"both-at-once","line":51,"column":0,"depth":3},"constants":{"type":"header","text":"Constants","value":"constants","line":53,"column":0,"depth":2},"blank-final-variable":{"type":"header","text":"Blank final variable","value":"blank-final-variable","line":57,"column":0,"depth":3},"ways-to-initialise":{"type":"header","text":"Ways to initialise","value":"ways-to-initialise","line":68,"column":0,"depth":4},"blank-static-final-membervariable":{"type":"header","text":"Blank static final member/variable","value":"blank-static-final-membervariable","line":76,"column":0,"depth":4},"initialisation":{"type":"header","text":"Initialisation","value":"initialisation","line":80,"column":0,"depth":5},"data-types":{"type":"header","text":"Data types","value":"data-types","line":85,"column":0,"depth":2},"primitives":{"type":"header","text":"Primitives","value":"primitives","line":87,"column":0,"depth":3},"suffixing-for-non-default-primitive-data-types":{"type":"header","text":"Suffixing for Non-default Primitive Data Types","value":"suffixing-for-non-default-primitive-data-types","line":106,"column":0,"depth":4},"prefixing-for-different-bases":{"type":"header","text":"Prefixing for Different Bases","value":"prefixing-for-different-bases","line":130,"column":0,"depth":4},"compound":{"type":"header","text":"Compound","value":"compound","line":137,"column":0,"depth":3},"array":{"type":"header","text":"Array","value":"array","line":139,"column":0,"depth":4},"declaration-1":{"type":"header","text":"Declaration","value":"declaration-1","line":141,"column":0,"depth":5},"initialization-1":{"type":"header","text":"Initialization","value":"initialization-1","line":152,"column":0,"depth":5},"strings":{"type":"header","text":"Strings","value":"strings","line":158,"column":0,"depth":4},"declaration-2":{"type":"header","text":"Declaration","value":"declaration-2","line":160,"column":0,"depth":5},"initialization-2":{"type":"header","text":"Initialization","value":"initialization-2","line":166,"column":0,"depth":5},"both-at-once-1":{"type":"header","text":"Both at once","value":"both-at-once-1","line":179,"column":0,"depth":5},"length":{"type":"header","text":"Length","value":"length","line":191,"column":0,"depth":5},"loopingcharacter-at-index":{"type":"header","text":"Looping/character at index","value":"loopingcharacter-at-index","line":197,"column":0,"depth":5},"structures":{"type":"header","text":"Structures","value":"structures","line":202,"column":0,"depth":4},"interfaces":{"type":"header","text":"Interfaces","value":"interfaces","line":203,"column":0,"depth":4},"classes":{"type":"header","text":"Classes","value":"classes","line":205,"column":0,"depth":4},"creating-objects":{"type":"header","text":"Creating objects","value":"creating-objects","line":207,"column":0,"depth":5},"using-objects":{"type":"header","text":"Using objects","value":"using-objects","line":221,"column":0,"depth":5},"operators":{"type":"header","text":"Operators","value":"operators","line":250,"column":0,"depth":2},"flow":{"type":"header","text":"Flow","value":"flow","line":252,"column":0,"depth":2},"conditionals":{"type":"header","text":"Conditionals","value":"conditionals","line":254,"column":0,"depth":3},"loops":{"type":"header","text":"Loops","value":"loops","line":256,"column":0,"depth":3},"functionsmethods":{"type":"header","text":"Functions/Methods","value":"functionsmethods","line":258,"column":0,"depth":2},"public-static-void-mainstring-args":{"type":"header","text":"public static void main(String[] args)","value":"public-static-void-mainstring-args","line":260,"column":0,"depth":3}},"children":[],"parent":"mrk0ypui29nso2bc2r99pok","data":{},"schema":{"schemaId":"syntax","moduleId":"lang"}}
