{"id":"ld57ynexk5ucd3q13g7t01b","title":"Controller","desc":"","updated":1719149752204,"created":1719138014223,"custom":{},"fname":"arch.modelling.roles.controller","type":"note","vault":{"fsPath":".","selfContained":true,"name":"cs"},"contentHash":"18b03d26fc9d17de90b8f682e31bae55","links":[{"type":"wiki","from":{"fname":"arch.modelling.roles.controller","id":"ld57ynexk5ucd3q13g7t01b","vaultName":"cs"},"value":"arch.modelling.roles.service","position":{"start":{"line":4,"column":38,"offset":116},"end":{"line":4,"column":70,"offset":148},"indent":[]},"xvault":false,"sameFile":false,"to":{"fname":"arch.modelling.roles.service"}},{"from":{"fname":"lang.java.spring.web.mvc","id":"hwuuss57w4hy7yl2w392pwb","vaultName":"cs"},"type":"backlink","position":{"start":{"line":12,"column":7,"offset":297},"end":{"line":12,"column":42,"offset":332},"indent":[]},"value":"arch.modelling.roles.controller"},{"from":{"fname":"lang.java.spring.web.mvc","id":"hwuuss57w4hy7yl2w392pwb","vaultName":"cs"},"type":"backlink","position":{"start":{"line":20,"column":17,"offset":519},"end":{"line":20,"column":52,"offset":554},"indent":[]},"value":"arch.modelling.roles.controller"}],"anchors":{},"children":[],"parent":"dlmq9nkp4fx5k01hxacntij","data":{}}
