{"id":"m5tnejfoc3gcy497nrw040l","title":"Out of Memory","desc":"","updated":1713813958598,"created":1713813603661,"custom":{},"fname":"dev.issues.error.out of memory","type":"note","vault":{"fsPath":".","selfContained":true,"name":"cs"},"contentHash":"c59b0611c55b21cb0cfb0b546b99375d","links":[{"type":"wiki","from":{"fname":"dev.issues.error.out of memory","id":"m5tnejfoc3gcy497nrw040l","vaultName":"cs"},"value":"dev.memory management.leaks","position":{"start":{"line":26,"column":6,"offset":1173},"end":{"line":26,"column":37,"offset":1204},"indent":[]},"xvault":false,"sameFile":false,"to":{"fname":"dev.memory management.leaks"}},{"type":"wiki","from":{"fname":"dev.issues.error.out of memory","id":"m5tnejfoc3gcy497nrw040l","vaultName":"cs"},"value":"os.memory.ram.user.heap","position":{"start":{"line":26,"column":41,"offset":1208},"end":{"line":26,"column":68,"offset":1235},"indent":[]},"xvault":false,"sameFile":false,"to":{"fname":"os.memory.ram.user.heap"}}],"anchors":{"common-causes":{"type":"header","text":"Common Causes","value":"common-causes","line":8,"column":0,"depth":2},"insufficient-ram":{"type":"header","text":"Insufficient RAM","value":"insufficient-ram","line":10,"column":0,"depth":3},"startup-programs":{"type":"header","text":"Startup Programs","value":"startup-programs","line":14,"column":0,"depth":3},"outdated-hardware":{"type":"header","text":"Outdated Hardware","value":"outdated-hardware","line":18,"column":0,"depth":3},"heavy-tasks":{"type":"header","text":"Heavy Tasks","value":"heavy-tasks","line":22,"column":0,"depth":3},"malware":{"type":"header","text":"Malware","value":"malware","line":26,"column":0,"depth":3},"memory-leaks":{"type":"header","text":"Memory Leaks","value":"memory-leaks","line":30,"column":0,"depth":3}},"children":[],"parent":"4a0ispi91a20vyl1hvjuom0","data":{}}
