{"id":"sm5xirmlx8xbwly5s4gjovp","title":"Imperative","desc":"","updated":1709733499247,"created":1708622041376,"custom":{},"fname":"paradigm.imperative","type":"note","vault":{"fsPath":".","selfContained":true,"name":"cs"},"contentHash":"b78fb5a56becd09199658d44951eba80","links":[{"type":"wiki","from":{"fname":"paradigm.imperative","id":"sm5xirmlx8xbwly5s4gjovp","vaultName":"cs"},"value":"paradigm.declarative","position":{"start":{"line":3,"column":40,"offset":41},"end":{"line":3,"column":64,"offset":65},"indent":[]},"xvault":false,"sameFile":false,"to":{"fname":"paradigm.declarative"}},{"from":{"fname":"paradigm.declarative","id":"63rgy8qmhxp9sjxvy63xr5q","vaultName":"cs"},"type":"backlink","position":{"start":{"line":3,"column":3,"offset":4},"end":{"line":3,"column":26,"offset":27},"indent":[]},"value":"paradigm.imperative"},{"from":{"fname":"paradigm.oo","id":"7omyctmyxe2f6ponjvfevkf","vaultName":"cs"},"type":"backlink","position":{"start":{"line":5,"column":3,"offset":49},"end":{"line":5,"column":26,"offset":72},"indent":[]},"value":"paradigm.imperative"}],"anchors":{"imperative":{"type":"header","text":"Imperative","value":"imperative","line":13,"column":0,"depth":2}},"children":[],"parent":"71sipcgr0pdqyxnmntvx28w","data":{},"schema":{"schemaId":"paradigm","moduleId":"paradigm"}}
