{"id":"wrii2qem89nle2t4xy32nsv","title":"String Builder","desc":"","updated":1712856299420,"created":1712856134364,"custom":{},"fname":"lang.java.lib.string.builder","type":"note","vault":{"fsPath":".","selfContained":true,"name":"cs"},"contentHash":"5f4064f1b5d947b454f7bcd5ded5b8f9","links":[{"type":"wiki","from":{"fname":"lang.java.lib.string.builder","id":"wrii2qem89nle2t4xy32nsv","vaultName":"cs"},"value":"lang.java.lib.string","position":{"start":{"line":4,"column":11,"offset":13},"end":{"line":4,"column":35,"offset":37},"indent":[]},"xvault":false,"sameFile":false,"to":{"fname":"lang.java.lib.string"}},{"type":"wiki","from":{"fname":"lang.java.lib.string.builder","id":"wrii2qem89nle2t4xy32nsv","vaultName":"cs"},"value":"lang.java.lib.string.buffer","position":{"start":{"line":5,"column":11,"offset":73},"end":{"line":5,"column":42,"offset":104},"indent":[]},"xvault":false,"sameFile":false,"to":{"fname":"lang.java.lib.string.buffer"}},{"from":{"fname":"lang.java.lib.string.buffer","id":"5kpsp95zn6nrn1y0k68w02w","vaultName":"cs"},"type":"backlink","position":{"start":{"line":4,"column":11,"offset":72},"end":{"line":4,"column":43,"offset":104},"indent":[]},"value":"lang.java.lib.string.builder"}],"anchors":{},"children":[],"parent":"vqbisdumti23oeq2xk6oml5","data":{}}
