{"id":"y2y38f39yfftv1xqtsjr07g","title":"Super","desc":"","updated":1708364690545,"created":1708364667683,"custom":{},"fname":"paradigm.oo.context.object.super","type":"note","vault":{"fsPath":".","selfContained":true,"name":"cs"},"contentHash":"6ad497094db8e26b82bd9aafb2fe5b5e","links":[{"type":"wiki","from":{"fname":"paradigm.oo.context.object.super","id":"y2y38f39yfftv1xqtsjr07g","vaultName":"cs"},"value":"paradigm.oo.context.object","position":{"start":{"line":5,"column":1,"offset":53},"end":{"line":5,"column":31,"offset":83},"indent":[]},"xvault":false,"sameFile":false,"to":{"fname":"paradigm.oo.context.object"}},{"from":{"fname":"lang.java.paradigms.oo.objects.context qualifiers","id":"azr712uwple6pv4sgkmrhyb","vaultName":"cs"},"type":"backlink","position":{"start":{"line":6,"column":13,"offset":127},"end":{"line":6,"column":49,"offset":163},"indent":[]},"value":"paradigm.oo.context.object.super"}],"anchors":{},"children":[],"parent":"6bsiamgbnsnol7s93ryy5a9","data":{}}
